MANIFEST.in
README.rst
setup.py
bootstrap_salt/__init__.py
bootstrap_salt/cloudformation.py
bootstrap_salt/config.py
bootstrap_salt/ec2.py
bootstrap_salt/errors.py
bootstrap_salt/fab_tasks.py
bootstrap_salt/kms.py
bootstrap_salt/salt_utils.py
bootstrap_salt/salt_utils_state.py
bootstrap_salt/salt_utils_update.py
bootstrap_salt/ssh.py
bootstrap_salt/utils.py
bootstrap_salt.egg-info/PKG-INFO
bootstrap_salt.egg-info/SOURCES.txt
bootstrap_salt.egg-info/dependency_links.txt
bootstrap_salt.egg-info/not-zip-safe
bootstrap_salt.egg-info/requires.txt
bootstrap_salt.egg-info/top_level.txt
bootstrap_salt/contrib/bootstrap.sh
bootstrap_salt/contrib/etc/salt/minion
bootstrap_salt/contrib/srv/salt/_grains/tags_to_grains.py
bootstrap_salt/contrib/usr/local/bin/salt_utils.py
bootstrap_salt/contrib/usr/local/bin/salt_utils_state.py
bootstrap_salt/contrib/usr/local/bin/salt_utils_update.py
bootstrap_salt/deploy_lib/__init__.py
bootstrap_salt/deploy_lib/github.py