Metadata-Version: 1.1
Name: bootstrap-salt
Version: 2.0.1
Summary: MOJDS salt bootstrap tool
Home-page: http://github.com/ministryofjustice/bootstrap-salt/
Author: MOJDS
Author-email: tools@digital.justice.gov.uk
License: LICENSE
Platform: any
Classifier: Development Status :: 3 - Alpha
Classifier: Environment :: Web Environment
Classifier: Intended Audience :: System Administrators
Classifier: Intended Audience :: Developers
Classifier: Operating System :: OS Independent
Classifier: Programming Language :: Python
Classifier: Programming Language :: Python :: 2
Classifier: Programming Language :: Python :: 2.6
Classifier: Programming Language :: Python :: 2.7
Classifier: Topic :: Software Development :: Libraries :: Python Modules
